mirage/__init__.py
mirage/crypto.py
mirage/exceptions.py
mirage/fields.py
mirage/tools.py
mirage/management/__init__.py
mirage/management/commands/__init__.py
mirage/management/commands/mirage.py
django_mirage_field-1.0.1.dist-info/LICENSE
django_mirage_field-1.0.1.dist-info/METADATA
django_mirage_field-1.0.1.dist-info/WHEEL
django_mirage_field-1.0.1.dist-info/top_level.txt
django_mirage_field-1.0.1.dist-info/RECORD
