Metadata-Version: 2.1
Name: django-mirage-field
Version: 1.0.1
Summary: A Django model field that encrypt your data when save to and decrypt when get from database. It keeps data always encrypted in database.
Home-page: https://github.com/luojilab/django-mirage-field
Author: tcitry
Author-email: tcitry@gmail.com
License: MIT License
Platform: UNKNOWN
Classifier: Environment :: Web Environment
Classifier: Framework :: Django
Classifier: Framework :: Django :: 1.8
Classifier: Framework :: Django :: 1.9
Classifier: Framework :: Django :: 1.10
Classifier: Framework :: Django :: 1.11
Classifier: Framework :: Django :: 2.0
Classifier: Framework :: Django :: 2.1
Classifier: Framework :: Django :: 2.2
Classifier: Intended Audience :: Developers
Classifier: License :: OSI Approved :: MIT License
Classifier: Operating System :: OS Independent
Classifier: Programming Language :: Python
Classifier: Programming Language :: Python :: 3.6
Classifier: Topic :: Internet :: WWW/HTTP
Requires-Dist: cryptography
Requires-Dist: tqdm
